polar/__init__.py
polar/polar.py
polar-0.0.118.dist-info/METADATA
polar-0.0.118.dist-info/WHEEL
polar-0.0.118.dist-info/top_level.txt
polar-0.0.118.dist-info/RECORD
