Metadata-Version: 2.1
Name: polar
Version: 0.0.118
Summary: Data Science Library
Home-page: https://pypi.org/project/polar/
Author: Piotr Parkitny
Author-email: pparkitn@gmail.com
License: UNKNOWN
Platform: UNKNOWN
Classifier: Programming Language :: Python :: 3
Classifier: License :: OSI Approved :: MIT License
Classifier: Operating System :: OS Independent
Requires-Python: >=3.5
Requires-Dist: pandas
Requires-Dist: numpy
Requires-Dist: scipy
Requires-Dist: statsmodels
Requires-Dist: sklearn
Requires-Dist: seaborn
Requires-Dist: scikit-learn
Requires-Dist: cryptography
Requires-Dist: nltk
Requires-Dist: python-pptx
Requires-Dist: imblearn
